<annotation>
	<folder>4Phones</folder>
	<filename>gcbv20200206_134552.jpg</filename>
	<path>C:\Users\MooreJ\Documents\APB\GaliTric\ImagesTrainTipper\4Phones\gcbv20200206_134552.jpg</path>
	<source>
		<database>Unknown</database>
	</source>
	<size>
		<width>2560</width>
		<height>1920</height>
		<depth>3</depth>
	</size>
	<segmented>0</segmented>
	<object>
		<name>BSSingle</name>
		<pose>Unspecified</pose>
		<truncated>0</truncated>
		<difficult>0</difficult>
		<bndbox>
			<xmin>948</xmin>
			<ymin>1042</ymin>
			<xmax>1000</xmax>
			<ymax>1094</ymax>
		</bndbox>
	</object>
	<object>
		<name>BSSingle</name>
		<pose>Unspecified</pose>
		<truncated>0</truncated>
		<difficult>0</difficult>
		<bndbox>
			<xmin>1351</xmin>
			<ymin>648</ymin>
			<xmax>1406</xmax>
			<ymax>702</ymax>
		</bndbox>
	</object>
	<object>
		<name>BS</name>
		<pose>Unspecified</pose>
		<truncated>0</truncated>
		<difficult>0</difficult>
		<bndbox>
			<xmin>1451</xmin>
			<ymin>1626</ymin>
			<xmax>1508</xmax>
			<ymax>1691</ymax>
		</bndbox>
	</object>
</annotation>
