<annotation>
	<folder>phase1_training</folder>
	<filename>70.jpg</filename>
	<path>D:\GrainCam\phase1_training\70.jpg</path>
	<source>
		<database>Unknown</database>
	</source>
	<size>
		<width>801</width>
		<height>608</height>
		<depth>3</depth>
	</size>
	<segmented>0</segmented>
	<object>
		<name>snail</name>
		<pose>Unspecified</pose>
		<truncated>0</truncated>
		<difficult>0</difficult>
		<bndbox>
			<xmin>188</xmin>
			<ymin>186</ymin>
			<xmax>202</xmax>
			<ymax>201</ymax>
		</bndbox>
	</object>
	<object>
		<name>snail</name>
		<pose>Unspecified</pose>
		<truncated>0</truncated>
		<difficult>0</difficult>
		<bndbox>
			<xmin>297</xmin>
			<ymin>235</ymin>
			<xmax>316</xmax>
			<ymax>243</ymax>
		</bndbox>
	</object>
	<object>
		<name>snail</name>
		<pose>Unspecified</pose>
		<truncated>0</truncated>
		<difficult>0</difficult>
		<bndbox>
			<xmin>519</xmin>
			<ymin>164</ymin>
			<xmax>529</xmax>
			<ymax>172</ymax>
		</bndbox>
	</object>
	<object>
		<name>snail</name>
		<pose>Unspecified</pose>
		<truncated>0</truncated>
		<difficult>0</difficult>
		<bndbox>
			<xmin>143</xmin>
			<ymin>322</ymin>
			<xmax>155</xmax>
			<ymax>338</ymax>
		</bndbox>
	</object>
	<object>
		<name>snail</name>
		<pose>Unspecified</pose>
		<truncated>0</truncated>
		<difficult>0</difficult>
		<bndbox>
			<xmin>53</xmin>
			<ymin>349</ymin>
			<xmax>71</xmax>
			<ymax>358</ymax>
		</bndbox>
	</object>
	<object>
		<name>snail</name>
		<pose>Unspecified</pose>
		<truncated>0</truncated>
		<difficult>0</difficult>
		<bndbox>
			<xmin>73</xmin>
			<ymin>371</ymin>
			<xmax>92</xmax>
			<ymax>380</ymax>
		</bndbox>
	</object>
	<object>
		<name>snail</name>
		<pose>Unspecified</pose>
		<truncated>0</truncated>
		<difficult>0</difficult>
		<bndbox>
			<xmin>439</xmin>
			<ymin>304</ymin>
			<xmax>456</xmax>
			<ymax>311</ymax>
		</bndbox>
	</object>
	<object>
		<name>snail</name>
		<pose>Unspecified</pose>
		<truncated>0</truncated>
		<difficult>0</difficult>
		<bndbox>
			<xmin>523</xmin>
			<ymin>404</ymin>
			<xmax>542</xmax>
			<ymax>413</ymax>
		</bndbox>
	</object>
	<object>
		<name>snail</name>
		<pose>Unspecified</pose>
		<truncated>0</truncated>
		<difficult>0</difficult>
		<bndbox>
			<xmin>36</xmin>
			<ymin>544</ymin>
			<xmax>59</xmax>
			<ymax>555</ymax>
		</bndbox>
	</object>
	<object>
		<name>snail</name>
		<pose>Unspecified</pose>
		<truncated>0</truncated>
		<difficult>0</difficult>
		<bndbox>
			<xmin>8</xmin>
			<ymin>564</ymin>
			<xmax>22</xmax>
			<ymax>577</ymax>
		</bndbox>
	</object>
	<object>
		<name>snail</name>
		<pose>Unspecified</pose>
		<truncated>0</truncated>
		<difficult>0</difficult>
		<bndbox>
			<xmin>105</xmin>
			<ymin>689</ymin>
			<xmax>128</xmax>
			<ymax>700</ymax>
		</bndbox>
	</object>
	<object>
		<name>snail</name>
		<pose>Unspecified</pose>
		<truncated>0</truncated>
		<difficult>0</difficult>
		<bndbox>
			<xmin>179</xmin>
			<ymin>698</ymin>
			<xmax>199</xmax>
			<ymax>716</ymax>
		</bndbox>
	</object>
	<object>
		<name>snail</name>
		<pose>Unspecified</pose>
		<truncated>0</truncated>
		<difficult>0</difficult>
		<bndbox>
			<xmin>776.0</xmin>
			<ymin>974.0</ymin>
			<xmax>793.0</xmax>
			<ymax>992.0</ymax>
		</bndbox>
	</object>
	<object>
		<name>snail</name>
		<pose>Unspecified</pose>
		<truncated>0</truncated>
		<difficult>0</difficult>
		<bndbox>
			<xmin>810.0</xmin>
			<ymin>985.0</ymin>
			<xmax>824.0</xmax>
			<ymax>999.0</ymax>
		</bndbox>
	</object>
	<object>
		<name>snail</name>
		<pose>Unspecified</pose>
		<truncated>0</truncated>
		<difficult>0</difficult>
		<bndbox>
			<xmin>151</xmin>
			<ymin>733</ymin>
			<xmax>175</xmax>
			<ymax>751</ymax>
		</bndbox>
	</object>
</annotation>