<annotation>
	<folder>phase1_training</folder>
	<filename>151.jpg</filename>
	<path>D:\GrainCam\phase1_training\151.jpg</path>
	<source>
		<database>Unknown</database>
	</source>
	<size>
		<width>3120</width>
		<height>4160</height>
		<depth>3</depth>
	</size>
	<segmented>0</segmented>
	<object>
		<name>snail</name>
		<pose>Unspecified</pose>
		<truncated>0</truncated>
		<difficult>0</difficult>
		<bndbox>
			<xmin>1354</xmin>
			<ymin>3016</ymin>
			<xmax>1410</xmax>
			<ymax>3080</ymax>
		</bndbox>
	</object>
	<object>
		<name>snail</name>
		<pose>Unspecified</pose>
		<truncated>0</truncated>
		<difficult>0</difficult>
		<bndbox>
			<xmin>761</xmin>
			<ymin>2724</ymin>
			<xmax>807</xmax>
			<ymax>2791</ymax>
		</bndbox>
	</object>
</annotation>
